oasis_workshop/__init__.py
oasis_workshop/client.py
oasis_workshop/funcs.py
oasis_workshop/session.py
oasis_workshop-1.0.0.dist-info/METADATA
oasis_workshop-1.0.0.dist-info/WHEEL
oasis_workshop-1.0.0.dist-info/top_level.txt
oasis_workshop-1.0.0.dist-info/RECORD
