Metadata-Version: 2.1
Name: oasis-workshop
Version: 1.0.0
Summary: Helper functions for oasis-workshop
Home-page: https://github.com/OasisLMF/Workshop2022
Author: Oasis LMF
Author-email: support@oasislmf.org
License: UNKNOWN
Platform: UNKNOWN
Requires-Python: >=3.7
Requires-Dist: requests
Requires-Dist: requests-toolbelt
Requires-Dist: tqdm
Requires-Dist: tabulate
Requires-Dist: pandas
Requires-Dist: altair
